LICENSE
MANIFEST.in
README
setup.py
docs/advanced_setup.txt
docs/caching.txt
docs/dotsmug.txt
docs/gitlib.txt
docs/simple_setup.txt
gitlib/__init__.py
gitlib/index.py
gitlib/objects.py
gitlib/repo.py
smug/__init__.py
smug/admin.py
smug/config.py
smug/dotsmug.py
smug/extras.py
smug/filters.py
smug/load.py
smug/menu.py
smug/models.py
smug/urls.py
smug.egg-info/PKG-INFO
smug.egg-info/SOURCES.txt
smug.egg-info/dependency_links.txt
smug.egg-info/top_level.txt
smug/blog/__init__.py
smug/blog/views.py
smug/pathops/__init__.py
smug/pathops/edit.py
smug/pathops/raw.py
smug/pathops/show.py
smug/templates/404.html
smug/templates/500.html
smug/templates/login.html
smug/templates/logout.html
smug/templates/smugform.html
smug/views/__init__.py
smug/views/login.py
smug/views/logout.py
smug/views/merge.py
smug/views/page.py
tests/caching_test.py
tests/gitlib_test.py