Metadata-Version: 1.1
Name: smug
Version: 0.6a3
Summary: smugly superior to wikis
Home-page: http://www.mcnabbs.org/andrew/smug/
Author: Andrew McNabb
Author-email: amcnabb@mcnabbs.org
License: GNU GPLv3 or later
Platform: linux
Platform: Apple OS X
Classifier: Development Status :: 4 - Beta
Classifier: Framework :: Django
Classifier: Intended Audience :: Developers
Classifier: Intended Audience :: Information Technology
Classifier: Intended Audience :: System Administrators
Classifier: License :: OSI Approved :: GNU General Public License (GPL)
Classifier: Operating System :: POSIX :: Linux
Classifier: Operating System :: MacOS :: MacOS X
Classifier: Programming Language :: Python
Classifier: Programming Language :: Python :: 2.4
Classifier: Programming Language :: Python :: 2.5
Classifier: Programming Language :: Python :: 2.6
Classifier: Topic :: Internet :: WWW/HTTP :: Dynamic Content
Classifier: Topic :: Internet :: WWW/HTTP :: WSGI :: Application
Classifier: Topic :: Software Development :: Version Control
Classifier: Topic :: Text Processing :: Markup
Requires: django
Provides: smug
Provides: gitlib
